imports/__init__.py
imports/imports.py
ScrapperImports-0.0.2.dist-info/LICENCE.txt
ScrapperImports-0.0.2.dist-info/METADATA
ScrapperImports-0.0.2.dist-info/WHEEL
ScrapperImports-0.0.2.dist-info/top_level.txt
ScrapperImports-0.0.2.dist-info/RECORD
