Metadata-Version: 2.1
Name: ScrapperImports
Version: 0.0.2
Summary: Imports all the necessary modules for scrapper
Home-page: https://github.com/pypa/sampleproject
Author: TimeSauce
Author-email: lorem.ipsum@gmail.com
License: UNKNOWN
Platform: UNKNOWN
Classifier: Programming Language :: Python :: 3
Classifier: License :: OSI Approved :: MIT License
Classifier: Operating System :: OS Independent
Requires-Python: >=3.6
